{
  "title": "List users in the system",
  "description": "",
  "permalink": "t~list~users~in~the~system~get~default~rdmp~api~users",
  "uuid": "9b89e4ad-a834-48b0-afd8-657dc6b20286",
  "method": "GET",
  "path": "/default/rdmp/api/users",
  "pathTemplate": "/default/rdmp/api/users",
  "parameters": [
    {
      "location": "query",
      "name": "page",
      "description": "The page number. Defaults to 1.",
      "required": true,
      "schema": {
        "type": "number"
      }
    },
    {
      "location": "query",
      "name": "pageSize",
      "description": "The number of results to return per page. Defaults to 10",
      "required": true,
      "schema": {
        "type": "number"
      }
    }
  ],
  "meta": {
    "resource": {
      "title": "List users in the system",
      "permalink": "r~list~users~in~the~system"
    }
  },
  "transactions": [
    {
      "request": {
        "title": "",
        "description": "",
        "method": "GET",
        "headers": []
      },
      "response": {
        "title": "",
        "description": "",
        "statusCode": "200",
        "contentType": "application/json",
        "headers": [
          {
            "name": "Content-Type",
            "example": "application/json",
            "required": false,
            "schema": {
              "type": "string"
            }
          }
        ],
        "body": "{\n\"summary\": {\n    \"numFound\": 1\n},\n\"records\": [\n    {\n        \"type\": \"local\",\n        \"name\": \"Local user\",\n        \"username\": \"user1\",\n        \"email\": \"localuser@redboxresearchdata.com.au\",\n        \"token\": \"16f613d9-29da-4326-a120-1ad70078f3c5\",\n        \"createdAt\": \"2017-10-09T03:34:47.660Z\",\n        \"updatedAt\": \"2017-11-20T04:08:33.061Z\",\n        \"id\": \"59daee5720b453050057c2f5\"\n    }\n]\n}\n\n"
      }
    }
  ]
}